pdf/PineconePDFExtractor.py
pdf/__init__.py
pdf/pdf_processor.py
PineconePDFExtractor-0.1.8.dist-info/LICENSE
PineconePDFExtractor-0.1.8.dist-info/METADATA
PineconePDFExtractor-0.1.8.dist-info/WHEEL
PineconePDFExtractor-0.1.8.dist-info/top_level.txt
PineconePDFExtractor-0.1.8.dist-info/RECORD
